reqsnaked-0.1.0b1.dist-info/METADATA
reqsnaked-0.1.0b1.dist-info/WHEEL
reqsnaked/__init__.py
reqsnaked/__init__.pyi
reqsnaked/py.typed
reqsnaked/reqsnaked.cp38-win_amd64.pyd
reqsnaked-0.1.0b1.dist-info/RECORD
