Metadata-Version: 2.1
Name: reqsnaked
Version: 0.1.0b1
Classifier: Programming Language :: Rust
Classifier: Programming Language :: Python :: Implementation :: CPython
Classifier: Programming Language :: Python :: Implementation :: PyPy
Requires-Dist: mkdocs==1.4.2; extra == 'docs'
Requires-Dist: mkdocs-material==9.0.14; extra == 'docs'
Requires-Dist: mike==1.1.2; extra == 'docs'
Requires-Dist: pillow==9.4.0; extra == 'docs'
Requires-Dist: cairosvg==2.6.0; extra == 'docs'
Requires-Dist: pytest==7.2.1; extra == 'test'
Requires-Dist: pytest-asyncio==0.20.3; extra == 'test'
Requires-Dist: aiohttp==3.8.4; extra == 'benchmark'
Requires-Dist: httpx==0.23.3; extra == 'benchmark'
Requires-Dist: pytest-benchmark==4.0.0; extra == 'benchmark'
Provides-Extra: docs
Provides-Extra: test
Provides-Extra: benchmark
Requires-Python: >=3.8
